pycleanarch/__init__.py
pycleanarch-0.0.3.dist-info/DESCRIPTION.rst
pycleanarch-0.0.3.dist-info/METADATA
pycleanarch-0.0.3.dist-info/RECORD
pycleanarch-0.0.3.dist-info/WHEEL
pycleanarch-0.0.3.dist-info/metadata.json
pycleanarch-0.0.3.dist-info/top_level.txt
