Metadata-Version: 2.0
Name: pycleanarch
Version: 0.0.3
Summary: A simple Python toolkit to work with Clean Architecture for Web 
Home-page: https://github.com/wallacesilva/pycleanarch
Author: Wallace Silva
Author-email: contato@wallacesilva.com
Maintainer: Wallace Silva
Maintainer-email: contato@wallacesilva.com
License: MIT License
Platform: UNKNOWN
Classifier: Programming Language :: Python :: 3
Classifier: License :: OSI Approved :: MIT License
Classifier: Intended Audience :: Developers
Classifier: Topic :: Software Development :: Libraries :: Python Modules
Classifier: Topic :: Software Development :: Quality Assurance
